PyScorecard/PyScorecard.py
PyScorecard/__init__.py
PyScorecard-0.2.1.dist-info/LICENSE.txt
PyScorecard-0.2.1.dist-info/METADATA
PyScorecard-0.2.1.dist-info/WHEEL
PyScorecard-0.2.1.dist-info/top_level.txt
PyScorecard-0.2.1.dist-info/RECORD
