Metadata-Version: 2.1
Name: PyScorecard
Version: 0.2.1
Summary: An unofficial API wrapper for the College Scorecard API.
Home-page: https://github.com/deino475/PyScorecard
Author: Nile Dixon
Author-email: niledixon475@gmail.com
License: GNU GPL-V2
Platform: UNKNOWN
Requires-Dist: requests
